{
    "timestamp": "2026-06-24T02:01:07.649101+00:00",
    "macro_bias": "NEUTRAL",
    "macro_score": 50,
    "dxy": {
        "price": 101.413,
        "ema20": 101.4149,
        "ema50": 101.4009,
        "ema_trend": "alcista",
        "structure_1h": "alcista",
        "structure_4h": "alcista",
        "momentum_slope": -0.002241,
        "momentum_state": "bajista",
        "breakout_24h": "none",
        "state_summary": "tendencia_fuerte"
    },
    "us10y": {
        "price": 4.493,
        "direction_1h": "cayendo",
        "momentum_state": "bajista"
    },
    "risk_environment": {
        "btc_probability_bias": "neutral",
        "altcoins_probability_bias": "neutral",
        "confidence_level": "media"
    },
    "alerts": {
        "macro_shift": true,
        "volatility_expansion": false
    }
}