{
    "timestamp": "2026-03-17T00:55:31.804861+00:00",
    "macro_bias": "RISK_OFF",
    "macro_score": 65,
    "dxy": {
        "price": 99.908,
        "ema20": 99.8736,
        "ema50": 99.841,
        "ema_trend": "alcista",
        "structure_1h": "alcista",
        "structure_4h": "alcista",
        "momentum_slope": 0.004759,
        "momentum_state": "alcista",
        "breakout_24h": "none",
        "state_summary": "tendencia_fuerte"
    },
    "us10y": {
        "price": 4.22,
        "direction_1h": "cayendo",
        "momentum_state": "bajista"
    },
    "risk_environment": {
        "btc_probability_bias": "bajista",
        "altcoins_probability_bias": "bajista",
        "confidence_level": "media"
    },
    "alerts": {
        "macro_shift": true,
        "volatility_expansion": false
    }
}