{
    "timestamp": "2026-03-24T21:58:18.803268+00:00",
    "macro_bias": "RISK_ON",
    "macro_score": 0,
    "dxy": {
        "price": 99.213,
        "ema20": 99.2524,
        "ema50": 99.317,
        "ema_trend": "bajista",
        "structure_1h": "neutral",
        "structure_4h": "bajista",
        "momentum_slope": -0.001493,
        "momentum_state": "bajista",
        "breakout_24h": "none",
        "state_summary": "rango_lateral"
    },
    "us10y": {
        "price": 4.392,
        "direction_1h": "cayendo",
        "momentum_state": "bajista"
    },
    "risk_environment": {
        "btc_probability_bias": "alcista",
        "altcoins_probability_bias": "alcista",
        "confidence_level": "alta"
    },
    "alerts": {
        "macro_shift": false,
        "volatility_expansion": false
    }
}