{
    "timestamp": "2026-03-25T11:56:39.419311+00:00",
    "macro_bias": "RISK_ON",
    "macro_score": 15,
    "dxy": {
        "price": 99.258,
        "ema20": 99.2776,
        "ema50": 99.2945,
        "ema_trend": "bajista",
        "structure_1h": "bajista",
        "structure_4h": "bajista",
        "momentum_slope": 0.000203,
        "momentum_state": "alcista",
        "breakout_24h": "none",
        "state_summary": "posible_reversion"
    },
    "us10y": {
        "price": 4.392,
        "direction_1h": "cayendo",
        "momentum_state": "bajista"
    },
    "risk_environment": {
        "btc_probability_bias": "alcista",
        "altcoins_probability_bias": "alcista",
        "confidence_level": "alta"
    },
    "alerts": {
        "macro_shift": false,
        "volatility_expansion": false
    }
}