{
    "timestamp": "2026-04-12T18:25:48.251667+00:00",
    "macro_bias": "RISK_ON",
    "macro_score": 30,
    "dxy": {
        "price": 98.698,
        "ema20": 98.6766,
        "ema50": 98.6778,
        "ema_trend": "bajista",
        "structure_1h": "alcista",
        "structure_4h": "neutral",
        "momentum_slope": 0.001433,
        "momentum_state": "alcista",
        "breakout_24h": "none",
        "state_summary": "consolidacion"
    },
    "us10y": {
        "price": 4.317,
        "direction_1h": "cayendo",
        "momentum_state": "bajista"
    },
    "risk_environment": {
        "btc_probability_bias": "alcista",
        "altcoins_probability_bias": "alcista",
        "confidence_level": "media"
    },
    "alerts": {
        "macro_shift": false,
        "volatility_expansion": false
    }
}