{
    "timestamp": "2026-03-06T05:57:00.592049+00:00",
    "macro_bias": "RISK_ON",
    "macro_score": 20,
    "dxy": {
        "price": 99.03,
        "ema20": 99.0206,
        "ema50": 99.051,
        "ema_trend": "bajista",
        "structure_1h": "neutral",
        "structure_4h": "neutral",
        "momentum_slope": -0.000374,
        "momentum_state": "bajista",
        "breakout_24h": "none",
        "state_summary": "rango_lateral"
    },
    "us10y": {
        "price": 4.146,
        "direction_1h": "subiendo",
        "momentum_state": "alcista"
    },
    "risk_environment": {
        "btc_probability_bias": "alcista",
        "altcoins_probability_bias": "alcista",
        "confidence_level": "media"
    },
    "alerts": {
        "macro_shift": false,
        "volatility_expansion": false
    }
}