{
  "meta": {
    "generated_at_utc": "2026-04-07T20:08:35.904804+00:00",
    "notes": [
      "Zero Nulls v3.2",
      "Macro Fallback Analysis active"
    ]
  },
  "macro_context_auto": {
    "macro_bias": "NEUTRAL",
    "macro_score": 50,
    "assets": {
      "DXY": {
        "price": 99.671,
        "trend": "bajista"
      },
      "US10Y": {
        "price": 4.343,
        "trend": "alcista"
      }
    }
  },
  "events_considered_titles": [
    "News from the Yahoo Finance Network",
    "JPMorgan has a stark message on the next Fed rate cut",
    "Is Merck & Co. (MRK) One of the Best Consistent Dividend Stocks to Buy Right Now?",
    "Circle Mints $1 Billion Of USDC Stablecoin In 24 Hours",
    "Gold IRA storage rules: IRS requirements for storing precious metals",
    "Citi Raises Exxon Mobil (XOM) Price Target on Middle East-Driven Energy Repricing",
    "Daily Spotlight: First-Quarter Segment Returns",
    "This Healthcare Stock Has No Debt and a Near-Monopoly in Its Market"
  ],
  "assets": {
    "BTCUSDT": {
      "context": {
        "asset": "BTCUSDT",
        "spot_price": 69350.96875,
        "perp_last_price": 69350.96875,
        "mark_price": 69350.96875,
        "index_price": 69350.96875,
        "funding_rate": 0.0001,
        "basis_pct_perp_minus_spot": 0.0
      },
      "final_micro": {
        "semaphore": "verde",
        "bias": "long",
        "probability_pct": 74,
        "technical_reasoning": [
          "Precio > EMA20",
          "RSI Bull"
        ],
        "entry_ideal": 69402.171875,
        "stop_loss_technical": 67755.734375,
        "target_1": 71871.828125,
        "target_2": 74341.484375,
        "note": "Operativa adaptativa basada en indicadores"
      },
      "final_macro": {
        "semaphore": "verde",
        "bias": "long",
        "probability_pct": 74,
        "technical_reasoning": [
          "Precio > EMA20",
          "RSI Bull"
        ],
        "entry_ideal": 69350.96875,
        "stop_loss_technical": 66281.5390625,
        "target_1": 73955.11328125,
        "target_2": 78559.2578125,
        "note": "Operativa adaptativa basada en indicadores"
      }
    },
    "SIRENUSDT": {
      "context": {
        "asset": "SIRENUSDT",
        "spot_price": 0.112,
        "perp_last_price": 0.112,
        "mark_price": 0.112,
        "index_price": 0.112,
        "funding_rate": 0.0001,
        "basis_pct_perp_minus_spot": 0.0
      },
      "final_micro": {
        "semaphore": "rojo",
        "bias": "no_trade",
        "probability_pct": 45,
        "technical_reasoning": [
          "Análisis de Sentimiento Macro (Sin Datos Técnicos)"
        ],
        "entry_ideal": 0.112,
        "stop_loss_technical": 0.11032,
        "target_1": 0.11452,
        "target_2": 0.11704,
        "note": "Operativa adaptativa basada en contexto macro"
      },
      "final_macro": {
        "semaphore": "rojo",
        "bias": "no_trade",
        "probability_pct": 45,
        "technical_reasoning": [
          "Análisis de Sentimiento Macro (Sin Datos Técnicos)"
        ],
        "entry_ideal": 0.112,
        "stop_loss_technical": 0.11032,
        "target_1": 0.11452,
        "target_2": 0.11704,
        "note": "Operativa adaptativa basada en contexto macro"
      }
    }
  }
}