{
  "meta": {
    "generated_at_utc": "2026-03-28T19:24:22.281737+00:00",
    "notes": [
      "Zero Nulls v3.2",
      "Macro Fallback Analysis active"
    ]
  },
  "macro_context_auto": {
    "macro_bias": "RISK_OFF",
    "macro_score": 80,
    "assets": {
      "DXY": {
        "price": 100.193,
        "trend": "alcista"
      },
      "US10Y": {
        "price": 4.44,
        "trend": "alcista"
      }
    }
  },
  "events_considered_titles": [
    "News from the Yahoo Finance Network",
    "Snap-on CEO Pinchuk: “Uncertain” Mechanics Shun Big-Ticket Tools Despite Booming Repairs",
    "Rising gas prices could be good news for EVs",
    "'Magnificent 7' stocks wipe more than $850 billion in value as stock market sell-off hits AI winners hard",
    "Almost everything is going wrong for markets right now",
    "Dow Jones Futures: Market Dives As Oil Prices Hit $100 In Iran War; What To Do Now",
    "Analyst Report: Paychex Inc",
    "Giving Your Kids A Down Payment Is Usually A Gift, But These In-Laws Made It A $300K 'Business Transaction.' For Dave Ramsey, It's A Nightmare"
  ],
  "assets": {
    "BTCUSDT": {
      "context": {
        "asset": "BTCUSDT",
        "spot_price": 66791.0234375,
        "perp_last_price": 66791.0234375,
        "mark_price": 66791.0234375,
        "index_price": 66791.0234375,
        "funding_rate": 0.0001,
        "basis_pct_perp_minus_spot": 0.0
      },
      "final_micro": {
        "semaphore": "verde",
        "bias": "short",
        "probability_pct": 95,
        "technical_reasoning": [
          "Precio < EMA20",
          "RSI Bear",
          "Macro RISK_OFF (Presión)"
        ],
        "entry_ideal": 66791.0234375,
        "stop_loss_technical": 67201.6484375,
        "target_1": 66175.0859375,
        "target_2": 65559.1484375,
        "note": "Operativa adaptativa basada en indicadores"
      },
      "final_macro": {
        "semaphore": "rojo",
        "bias": "no_trade",
        "probability_pct": 45,
        "technical_reasoning": [
          "Precio > EMA20",
          "Macro RISK_OFF (Presión)"
        ],
        "entry_ideal": 66791.0234375,
        "stop_loss_technical": 65789.15808594,
        "target_1": 68293.82146484,
        "target_2": 69796.61949219,
        "note": "Operativa adaptativa basada en indicadores"
      }
    },
    "SIRENUSDT": {
      "context": {
        "asset": "SIRENUSDT",
        "spot_price": 0.112,
        "perp_last_price": 0.112,
        "mark_price": 0.112,
        "index_price": 0.112,
        "funding_rate": 0.0001,
        "basis_pct_perp_minus_spot": 0.0
      },
      "final_micro": {
        "semaphore": "verde",
        "bias": "short",
        "probability_pct": 74,
        "technical_reasoning": [
          "Macro RISK_OFF (Presión)",
          "Análisis de Sentimiento Macro (Sin Datos Técnicos)"
        ],
        "entry_ideal": 0.112,
        "stop_loss_technical": 0.11368,
        "target_1": 0.10948,
        "target_2": 0.10696,
        "note": "Operativa adaptativa basada en contexto macro"
      },
      "final_macro": {
        "semaphore": "verde",
        "bias": "short",
        "probability_pct": 74,
        "technical_reasoning": [
          "Macro RISK_OFF (Presión)",
          "Análisis de Sentimiento Macro (Sin Datos Técnicos)"
        ],
        "entry_ideal": 0.112,
        "stop_loss_technical": 0.11368,
        "target_1": 0.10948,
        "target_2": 0.10696,
        "note": "Operativa adaptativa basada en contexto macro"
      }
    }
  }
}