{
  "meta": {
    "generated_at_utc": "2026-04-28T18:02:44.095639+00:00",
    "notes": [
      "Zero Nulls v3.2",
      "Macro Fallback Analysis active"
    ]
  },
  "macro_context_auto": {
    "macro_bias": "NEUTRAL",
    "macro_score": 50,
    "assets": {
      "DXY": {
        "price": 98.609,
        "trend": "bajista"
      },
      "US10Y": {
        "price": 4.359,
        "trend": "alcista"
      }
    }
  },
  "events_considered_titles": [
    "U.S. markets close in 1h 58m",
    "News from the Yahoo Finance Network",
    "Elon Musk Claims People Won’t Need Retirement Savings Because of AI: ‘It Won’t Matter’",
    "Bill Maher blasts America’s $5T tax monster: ‘Almost 60%’ of his income goes to Uncle Sam while the poor still suffer",
    "GM Expects $500 Million Tariff Refund—Boosting 2026 Earnings Estimates",
    "Nicola Mining Starts Exploration Drilling at Its Flagship New Craigmont Copper Project",
    "UBS Group AG (UBS) Against Swiss Government’s New $22B Capital Requirement",
    "Warren Buffett Once Said If Your Kids Read Your Will After You're Gone, You've Already Made A 'Terrible Mistake' — Here's Why"
  ],
  "assets": {
    "BTCUSDT": {
      "context": {
        "asset": "BTCUSDT",
        "spot_price": 76163.0703125,
        "perp_last_price": 76163.0703125,
        "mark_price": 76163.0703125,
        "index_price": 76163.0703125,
        "funding_rate": 0.0001,
        "basis_pct_perp_minus_spot": 0.0
      },
      "final_micro": {
        "semaphore": "verde",
        "bias": "long",
        "probability_pct": 74,
        "technical_reasoning": [
          "Precio > EMA20",
          "RSI Bull"
        ],
        "entry_ideal": 76160.0,
        "stop_loss_technical": 75653.7578125,
        "target_1": 76919.36328125,
        "target_2": 77678.7265625,
        "note": "Operativa adaptativa basada en indicadores"
      },
      "final_macro": {
        "semaphore": "verde",
        "bias": "short",
        "probability_pct": 74,
        "technical_reasoning": [
          "Precio < EMA20",
          "RSI Bear"
        ],
        "entry_ideal": 76163.0703125,
        "stop_loss_technical": 79488.171875,
        "target_1": 71175.41796875,
        "target_2": 66187.765625,
        "note": "Operativa adaptativa basada en indicadores"
      }
    },
    "SIRENUSDT": {
      "context": {
        "asset": "SIRENUSDT",
        "spot_price": 0.112,
        "perp_last_price": 0.112,
        "mark_price": 0.112,
        "index_price": 0.112,
        "funding_rate": 0.0001,
        "basis_pct_perp_minus_spot": 0.0
      },
      "final_micro": {
        "semaphore": "rojo",
        "bias": "no_trade",
        "probability_pct": 45,
        "technical_reasoning": [
          "Análisis de Sentimiento Macro (Sin Datos Técnicos)"
        ],
        "entry_ideal": 0.112,
        "stop_loss_technical": 0.11032,
        "target_1": 0.11452,
        "target_2": 0.11704,
        "note": "Operativa adaptativa basada en contexto macro"
      },
      "final_macro": {
        "semaphore": "rojo",
        "bias": "no_trade",
        "probability_pct": 45,
        "technical_reasoning": [
          "Análisis de Sentimiento Macro (Sin Datos Técnicos)"
        ],
        "entry_ideal": 0.112,
        "stop_loss_technical": 0.11032,
        "target_1": 0.11452,
        "target_2": 0.11704,
        "note": "Operativa adaptativa basada en contexto macro"
      }
    }
  }
}