{
  "meta": {
    "generated_at_utc": "2026-04-24T03:43:31.572488+00:00",
    "notes": [
      "Zero Nulls v3.2",
      "Macro Fallback Analysis active"
    ]
  },
  "macro_context_auto": {
    "macro_bias": "RISK_OFF",
    "macro_score": 80,
    "assets": {
      "DXY": {
        "price": 98.906,
        "trend": "alcista"
      },
      "US10Y": {
        "price": 4.323,
        "trend": "alcista"
      }
    }
  },
  "events_considered_titles": [
    "News from the Yahoo Finance Network",
    "Honda CEO says 'we have no chance' against Chinese automakers",
    "Warren Buffett's Surprising Take on Social Security That Every Investor Should Know",
    "1 Oversold Stock Set for a Comeback and 2 We Avoid",
    "A Trump Bull Market Correction May Be Coming. Here's What 150 Years of Data Says.",
    "Elon Musk Admits He Lied to Tesla Customers’ Faces for Years About Self-Driving",
    "Sam's Club just gave members a reason to ditch Costco",
    "American soldier arrested over Polymarket wagers tied to Maduro's capture"
  ],
  "assets": {
    "BTCUSDT": {
      "context": {
        "asset": "BTCUSDT",
        "spot_price": 77666.46875,
        "perp_last_price": 77666.46875,
        "mark_price": 77666.46875,
        "index_price": 77666.46875,
        "funding_rate": 0.0001,
        "basis_pct_perp_minus_spot": 0.0
      },
      "final_micro": {
        "semaphore": "verde",
        "bias": "short",
        "probability_pct": 95,
        "technical_reasoning": [
          "Precio < EMA20",
          "RSI Bear",
          "Macro RISK_OFF (Presión)"
        ],
        "entry_ideal": 77664.0078125,
        "stop_loss_technical": 78716.328125,
        "target_1": 76085.52734375,
        "target_2": 74507.046875,
        "note": "Operativa adaptativa basada en indicadores"
      },
      "final_macro": {
        "semaphore": "verde",
        "bias": "short",
        "probability_pct": 95,
        "technical_reasoning": [
          "Precio < EMA20",
          "RSI Bear",
          "Macro RISK_OFF (Presión)"
        ],
        "entry_ideal": 77666.46875,
        "stop_loss_technical": 79468.0,
        "target_1": 74964.171875,
        "target_2": 72261.875,
        "note": "Operativa adaptativa basada en indicadores"
      }
    },
    "SIRENUSDT": {
      "context": {
        "asset": "SIRENUSDT",
        "spot_price": 0.112,
        "perp_last_price": 0.112,
        "mark_price": 0.112,
        "index_price": 0.112,
        "funding_rate": 0.0001,
        "basis_pct_perp_minus_spot": 0.0
      },
      "final_micro": {
        "semaphore": "verde",
        "bias": "short",
        "probability_pct": 74,
        "technical_reasoning": [
          "Macro RISK_OFF (Presión)",
          "Análisis de Sentimiento Macro (Sin Datos Técnicos)"
        ],
        "entry_ideal": 0.112,
        "stop_loss_technical": 0.11368,
        "target_1": 0.10948,
        "target_2": 0.10696,
        "note": "Operativa adaptativa basada en contexto macro"
      },
      "final_macro": {
        "semaphore": "verde",
        "bias": "short",
        "probability_pct": 74,
        "technical_reasoning": [
          "Macro RISK_OFF (Presión)",
          "Análisis de Sentimiento Macro (Sin Datos Técnicos)"
        ],
        "entry_ideal": 0.112,
        "stop_loss_technical": 0.11368,
        "target_1": 0.10948,
        "target_2": 0.10696,
        "note": "Operativa adaptativa basada en contexto macro"
      }
    }
  }
}