{
  "meta": {
    "generated_at_utc": "2026-04-12T07:42:22.654874+00:00",
    "notes": [
      "Zero Nulls v3.2",
      "Macro Fallback Analysis active"
    ]
  },
  "macro_context_auto": {
    "macro_bias": "NEUTRAL",
    "macro_score": 50,
    "assets": {
      "DXY": {
        "price": 98.698,
        "trend": "bajista"
      },
      "US10Y": {
        "price": 4.317,
        "trend": "alcista"
      }
    }
  },
  "events_considered_titles": [
    "News from the Yahoo Finance Network",
    "Millionaires in America: How common is it to have a 7-figure net worth?",
    "The Vanguard ETF That Could Set You Up for Life if You Buy It in April",
    "Iconic steakhouse chain is making a comeback after nearly fading away",
    "How Much You Really Need Invested to Replace a $100,000 Salary With Dividends",
    "McDonald's quietly makes 2 menu changes customers may not like",
    "Here's the salary you need to afford a $1 million home",
    "‘Big Short’ Michael Burry sends signal on Nvidia stock"
  ],
  "assets": {
    "BTCUSDT": {
      "context": {
        "asset": "BTCUSDT",
        "spot_price": 71730.5390625,
        "perp_last_price": 71730.5390625,
        "mark_price": 71730.5390625,
        "index_price": 71730.5390625,
        "funding_rate": 0.0001,
        "basis_pct_perp_minus_spot": 0.0
      },
      "final_micro": {
        "semaphore": "verde",
        "bias": "long",
        "probability_pct": 74,
        "technical_reasoning": [
          "Precio > EMA20",
          "RSI Bull"
        ],
        "entry_ideal": 71730.5390625,
        "stop_loss_technical": 71464.046875,
        "target_1": 72130.27734375,
        "target_2": 72530.015625,
        "note": "Operativa adaptativa basada en indicadores"
      },
      "final_macro": {
        "semaphore": "verde",
        "bias": "short",
        "probability_pct": 74,
        "technical_reasoning": [
          "Precio < EMA20",
          "RSI Bear"
        ],
        "entry_ideal": 71730.5390625,
        "stop_loss_technical": 73784.234375,
        "target_1": 68649.99609375,
        "target_2": 65569.453125,
        "note": "Operativa adaptativa basada en indicadores"
      }
    },
    "SIRENUSDT": {
      "context": {
        "asset": "SIRENUSDT",
        "spot_price": 0.112,
        "perp_last_price": 0.112,
        "mark_price": 0.112,
        "index_price": 0.112,
        "funding_rate": 0.0001,
        "basis_pct_perp_minus_spot": 0.0
      },
      "final_micro": {
        "semaphore": "rojo",
        "bias": "no_trade",
        "probability_pct": 45,
        "technical_reasoning": [
          "Análisis de Sentimiento Macro (Sin Datos Técnicos)"
        ],
        "entry_ideal": 0.112,
        "stop_loss_technical": 0.11032,
        "target_1": 0.11452,
        "target_2": 0.11704,
        "note": "Operativa adaptativa basada en contexto macro"
      },
      "final_macro": {
        "semaphore": "rojo",
        "bias": "no_trade",
        "probability_pct": 45,
        "technical_reasoning": [
          "Análisis de Sentimiento Macro (Sin Datos Técnicos)"
        ],
        "entry_ideal": 0.112,
        "stop_loss_technical": 0.11032,
        "target_1": 0.11452,
        "target_2": 0.11704,
        "note": "Operativa adaptativa basada en contexto macro"
      }
    }
  }
}