{
  "meta": {
    "generated_at_utc": "2026-07-23T12:56:12.786270+00:00",
    "notes": [
      "Zero Nulls v3.2",
      "Macro Fallback Analysis active"
    ]
  },
  "macro_context_auto": {
    "macro_bias": "RISK_OFF",
    "macro_score": 80,
    "assets": {
      "DXY": {
        "price": 101.412,
        "trend": "alcista"
      },
      "US10Y": {
        "price": 4.707,
        "trend": "alcista"
      }
    }
  },
  "events_considered_titles": [
    "News from the Yahoo Finance Network",
    "Tesla Misses Badly on Earnings as Free Cash Flow Turns Negative",
    "Google’s New Chip in the Works May Run AI Up to 10x Cheaper — Why This Efficiency Breakthrough Makes the Stock a Screaming Buy",
    "JPMorgan CEO Jamie Dimon Just Issued a Stark Warning About Long-Term US Bonds: 'I Would Not Be a Buyer...'",
    "How to Retire Comfortably in Asia: Getting the Most from Social Security in Thailand",
    "Michael Burry's $39 a month Substack hits 300,000 subscribers, fueling speculation of a $113M-a-year newsletter empire",
    "Popular’s (NASDAQ:BPOP) Q2 CY2026 Sales Beat Estimates",
    "Paramount Skydance Wins EU Approval for Warner Bros. Discovery Deal After Offering This Key Concession— but US Hurdles Loom"
  ],
  "assets": {
    "BTCUSDT": {
      "context": {
        "asset": "BTCUSDT",
        "spot_price": 65177.48046875,
        "perp_last_price": 65177.48046875,
        "mark_price": 65177.48046875,
        "index_price": 65177.48046875,
        "funding_rate": 0.0001,
        "basis_pct_perp_minus_spot": 0.0
      },
      "final_micro": {
        "semaphore": "verde",
        "bias": "short",
        "probability_pct": 95,
        "technical_reasoning": [
          "Precio < EMA20",
          "RSI Bear",
          "Macro RISK_OFF (Presión)"
        ],
        "entry_ideal": 65175.2109375,
        "stop_loss_technical": 66280.609375,
        "target_1": 63517.11328125,
        "target_2": 61859.015625,
        "note": "Operativa adaptativa basada en indicadores"
      },
      "final_macro": {
        "semaphore": "verde",
        "bias": "short",
        "probability_pct": 95,
        "technical_reasoning": [
          "Precio < EMA20",
          "RSI Bear",
          "Macro RISK_OFF (Presión)"
        ],
        "entry_ideal": 65177.48046875,
        "stop_loss_technical": 66910.0625,
        "target_1": 62578.60742188,
        "target_2": 59979.734375,
        "note": "Operativa adaptativa basada en indicadores"
      }
    },
    "SIRENUSDT": {
      "context": {
        "asset": "SIRENUSDT",
        "spot_price": 0.112,
        "perp_last_price": 0.112,
        "mark_price": 0.112,
        "index_price": 0.112,
        "funding_rate": 0.0001,
        "basis_pct_perp_minus_spot": 0.0
      },
      "final_micro": {
        "semaphore": "verde",
        "bias": "short",
        "probability_pct": 74,
        "technical_reasoning": [
          "Macro RISK_OFF (Presión)",
          "Análisis de Sentimiento Macro (Sin Datos Técnicos)"
        ],
        "entry_ideal": 0.112,
        "stop_loss_technical": 0.11368,
        "target_1": 0.10948,
        "target_2": 0.10696,
        "note": "Operativa adaptativa basada en contexto macro"
      },
      "final_macro": {
        "semaphore": "verde",
        "bias": "short",
        "probability_pct": 74,
        "technical_reasoning": [
          "Macro RISK_OFF (Presión)",
          "Análisis de Sentimiento Macro (Sin Datos Técnicos)"
        ],
        "entry_ideal": 0.112,
        "stop_loss_technical": 0.11368,
        "target_1": 0.10948,
        "target_2": 0.10696,
        "note": "Operativa adaptativa basada en contexto macro"
      }
    }
  }
}