{
  "meta": {
    "generated_at_utc": "2026-07-04T23:36:29.148835+00:00",
    "notes": [
      "Zero Nulls v3.2",
      "Macro Fallback Analysis active"
    ]
  },
  "macro_context_auto": {
    "macro_bias": "NEUTRAL",
    "macro_score": 50,
    "assets": {
      "DXY": {
        "price": 100.8,
        "trend": "bajista"
      },
      "US10Y": {
        "price": 4.485,
        "trend": "alcista"
      }
    }
  },
  "events_considered_titles": [
    "News from the Yahoo Finance Network",
    "The Smartest Dividend Stock to Buy With $1,000 Right Now",
    "Millionaires in America: How common is it to have a 7-figure net worth?",
    "Social Security's 2027 COLA Is on Pace for a Historic \"Trump Bump\" -- but It Comes With Unintended Consequences",
    "Here's who won — and lost — under Trump's \"big, beautiful bill\"",
    "Prediction: SpaceX Stock Will Hit This Price by the End of 2026",
    "Here's How Many Shares of Coca-Cola You'd Need for $5,000 in Yearly Dividends",
    "Largest Data Center Project Ever Proposed Is Officially Dead"
  ],
  "assets": {
    "BTCUSDT": {
      "context": {
        "asset": "BTCUSDT",
        "spot_price": 63085.12109375,
        "perp_last_price": 63085.12109375,
        "mark_price": 63085.12109375,
        "index_price": 63085.12109375,
        "funding_rate": 0.0001,
        "basis_pct_perp_minus_spot": 0.0
      },
      "final_micro": {
        "semaphore": "amarillo",
        "bias": "long",
        "probability_pct": 66,
        "technical_reasoning": [
          "Precio > EMA20"
        ],
        "entry_ideal": 63085.12109375,
        "stop_loss_technical": 62274.16015625,
        "target_1": 64301.5625,
        "target_2": 65518.00390625,
        "note": "Operativa adaptativa basada en indicadores"
      },
      "final_macro": {
        "semaphore": "verde",
        "bias": "long",
        "probability_pct": 74,
        "technical_reasoning": [
          "Precio > EMA20",
          "RSI Bull"
        ],
        "entry_ideal": 63085.12109375,
        "stop_loss_technical": 57747.765625,
        "target_1": 71091.15429688,
        "target_2": 79097.1875,
        "note": "Operativa adaptativa basada en indicadores"
      }
    },
    "SIRENUSDT": {
      "context": {
        "asset": "SIRENUSDT",
        "spot_price": 0.112,
        "perp_last_price": 0.112,
        "mark_price": 0.112,
        "index_price": 0.112,
        "funding_rate": 0.0001,
        "basis_pct_perp_minus_spot": 0.0
      },
      "final_micro": {
        "semaphore": "rojo",
        "bias": "no_trade",
        "probability_pct": 45,
        "technical_reasoning": [
          "Análisis de Sentimiento Macro (Sin Datos Técnicos)"
        ],
        "entry_ideal": 0.112,
        "stop_loss_technical": 0.11032,
        "target_1": 0.11452,
        "target_2": 0.11704,
        "note": "Operativa adaptativa basada en contexto macro"
      },
      "final_macro": {
        "semaphore": "rojo",
        "bias": "no_trade",
        "probability_pct": 45,
        "technical_reasoning": [
          "Análisis de Sentimiento Macro (Sin Datos Técnicos)"
        ],
        "entry_ideal": 0.112,
        "stop_loss_technical": 0.11032,
        "target_1": 0.11452,
        "target_2": 0.11704,
        "note": "Operativa adaptativa basada en contexto macro"
      }
    }
  }
}