{
  "meta": {
    "generated_at_utc": "2026-06-04T17:24:40.302361+00:00",
    "notes": [
      "Zero Nulls v3.2",
      "Macro Fallback Analysis active"
    ]
  },
  "macro_context_auto": {
    "macro_bias": "NEUTRAL",
    "macro_score": 50,
    "assets": {
      "DXY": {
        "price": 99.366,
        "trend": "alcista"
      },
      "US10Y": {
        "price": 4.469,
        "trend": "bajista"
      }
    }
  },
  "events_considered_titles": [
    "U.S. markets close in 2h 36m",
    "News from the Yahoo Finance Network",
    "What IBM's $10-Billion Quantum Project Means For Smaller Players",
    "3 Absurdly Cheap Dividend Stocks to Buy With $1,000 Right Now",
    "Is It Too Late To Consider Nokia Oyj (HLSE:NOKIA) After Its 220% One-Year Surge?",
    "Market Chatter: General Motors Rehires Over 100 Former Cruise Team Members",
    "Is It Time To Reassess Stantec (TSX:STN) After The Recent Share Price Slump",
    "Mark Cuban dumped most of his Bitcoin, saying it 'lost the plot.' Experts say he panic-sold at the worst possible time"
  ],
  "assets": {
    "BTCUSDT": {
      "context": {
        "asset": "BTCUSDT",
        "spot_price": 63085.0390625,
        "perp_last_price": 63085.0390625,
        "mark_price": 63085.0390625,
        "index_price": 63085.0390625,
        "funding_rate": 0.0001,
        "basis_pct_perp_minus_spot": 0.0
      },
      "final_micro": {
        "semaphore": "verde",
        "bias": "short",
        "probability_pct": 74,
        "technical_reasoning": [
          "Precio < EMA20",
          "RSI Bear"
        ],
        "entry_ideal": 63108.96875,
        "stop_loss_technical": 65717.1328125,
        "target_1": 59196.72265625,
        "target_2": 55284.4765625,
        "note": "Operativa adaptativa basada en indicadores"
      },
      "final_macro": {
        "semaphore": "verde",
        "bias": "short",
        "probability_pct": 74,
        "technical_reasoning": [
          "Precio < EMA20",
          "RSI Bear"
        ],
        "entry_ideal": 63085.0390625,
        "stop_loss_technical": 74153.5,
        "target_1": 46482.34765625,
        "target_2": 29879.65625,
        "note": "Operativa adaptativa basada en indicadores"
      }
    },
    "SIRENUSDT": {
      "context": {
        "asset": "SIRENUSDT",
        "spot_price": 0.112,
        "perp_last_price": 0.112,
        "mark_price": 0.112,
        "index_price": 0.112,
        "funding_rate": 0.0001,
        "basis_pct_perp_minus_spot": 0.0
      },
      "final_micro": {
        "semaphore": "rojo",
        "bias": "no_trade",
        "probability_pct": 45,
        "technical_reasoning": [
          "Análisis de Sentimiento Macro (Sin Datos Técnicos)"
        ],
        "entry_ideal": 0.112,
        "stop_loss_technical": 0.11032,
        "target_1": 0.11452,
        "target_2": 0.11704,
        "note": "Operativa adaptativa basada en contexto macro"
      },
      "final_macro": {
        "semaphore": "rojo",
        "bias": "no_trade",
        "probability_pct": 45,
        "technical_reasoning": [
          "Análisis de Sentimiento Macro (Sin Datos Técnicos)"
        ],
        "entry_ideal": 0.112,
        "stop_loss_technical": 0.11032,
        "target_1": 0.11452,
        "target_2": 0.11704,
        "note": "Operativa adaptativa basada en contexto macro"
      }
    }
  }
}