{
  "meta": {
    "generated_at_utc": "2026-05-12T10:09:34.716072+00:00",
    "notes": [
      "Zero Nulls v3.2",
      "Macro Fallback Analysis active"
    ]
  },
  "macro_context_auto": {
    "macro_bias": "RISK_OFF",
    "macro_score": 80,
    "assets": {
      "DXY": {
        "price": 98.248,
        "trend": "alcista"
      },
      "US10Y": {
        "price": 4.41,
        "trend": "alcista"
      }
    }
  },
  "events_considered_titles": [
    "U.S. markets open in 3h 21m",
    "News from the Yahoo Finance Network",
    "7 Billionaires Are Betting Big on This Quantum Computing Powerhouse -- and It's Not IonQ or D‑Wave",
    "'Big Short' investor Michael Burry says the market has 'jumped the shark' — what he says investors are getting wrong",
    "Prediction: This Could Be Nvidia's Stock Price By the End of 2027",
    "Quantum Computing Stocks IonQ and D-Wave Quantum Have Nearly Doubled in 5 Weeks -- Don't Take the Bait",
    "LNC Q1 Deep Dive: Revenue Growth Outpaces Profitability amid Market Headwinds",
    "I Examined More Than 100 U.S. Dividend ETFs. This One Delivers the Best Risk-Adjusted Returns."
  ],
  "assets": {
    "BTCUSDT": {
      "context": {
        "asset": "BTCUSDT",
        "spot_price": 80789.546875,
        "perp_last_price": 80789.546875,
        "mark_price": 80789.546875,
        "index_price": 80789.546875,
        "funding_rate": 0.0001,
        "basis_pct_perp_minus_spot": 0.0
      },
      "final_micro": {
        "semaphore": "verde",
        "bias": "short",
        "probability_pct": 90,
        "technical_reasoning": [
          "Precio < EMA20",
          "Macro RISK_OFF (Presión)"
        ],
        "entry_ideal": 80786.046875,
        "stop_loss_technical": 82131.171875,
        "target_1": 78768.359375,
        "target_2": 76750.671875,
        "note": "Operativa adaptativa basada en indicadores"
      },
      "final_macro": {
        "semaphore": "verde",
        "bias": "short",
        "probability_pct": 95,
        "technical_reasoning": [
          "Precio < EMA20",
          "RSI Bear",
          "Macro RISK_OFF (Presión)"
        ],
        "entry_ideal": 80789.546875,
        "stop_loss_technical": 82430.171875,
        "target_1": 78328.609375,
        "target_2": 75867.671875,
        "note": "Operativa adaptativa basada en indicadores"
      }
    },
    "SIRENUSDT": {
      "context": {
        "asset": "SIRENUSDT",
        "spot_price": 0.112,
        "perp_last_price": 0.112,
        "mark_price": 0.112,
        "index_price": 0.112,
        "funding_rate": 0.0001,
        "basis_pct_perp_minus_spot": 0.0
      },
      "final_micro": {
        "semaphore": "verde",
        "bias": "short",
        "probability_pct": 74,
        "technical_reasoning": [
          "Macro RISK_OFF (Presión)",
          "Análisis de Sentimiento Macro (Sin Datos Técnicos)"
        ],
        "entry_ideal": 0.112,
        "stop_loss_technical": 0.11368,
        "target_1": 0.10948,
        "target_2": 0.10696,
        "note": "Operativa adaptativa basada en contexto macro"
      },
      "final_macro": {
        "semaphore": "verde",
        "bias": "short",
        "probability_pct": 74,
        "technical_reasoning": [
          "Macro RISK_OFF (Presión)",
          "Análisis de Sentimiento Macro (Sin Datos Técnicos)"
        ],
        "entry_ideal": 0.112,
        "stop_loss_technical": 0.11368,
        "target_1": 0.10948,
        "target_2": 0.10696,
        "note": "Operativa adaptativa basada en contexto macro"
      }
    }
  }
}